fans/__init__.py
fans/bunch.py
fans/datelib.py
fans/deco.py
fans/enodoc.py
fans/errors.py
fans/fmt.py
fans/fn.py
fans/logger.py
fans/osync.py
fans/poll.py
fans/ports.py
fans/progress.py
fans/progress_test.py
fans/retry.py
fans/sci.py
fans/struc.py
fans/tail.py
fans/test_vectorized.py
fans/testutil.py
fans/timing.py
fans/vectorized.py
fans/algorithm/__init__.py
fans/cacheutil/__init__.py
fans/cacheutil/file_cached.py
fans/collection/__init__.py
fans/collection/domaindict.py
fans/collection/test_domaindict.py
fans/db/__init__.py
fans/db/migrate.py
fans/db/tests/__init__.py
fans/db/tests/test_migrate.py
fans/dbutil/__init__.py
fans/dbutil/tagging/__init__.py
fans/dbutil/tagging/parse.py
fans/dbutil/tagging/tagging.py
fans/dbutil/tagging/test_tagging.py
fans/doy/cons.py
fans/jober/__init__.py
fans/jober/__main__.py
fans/jober/app.py
fans/jober/capture.py
fans/jober/job.py
fans/jober/jober.py
fans/jober/run.py
fans/jober/sched.py
fans/jober/target.py
fans/jober/tests/__init__.py
fans/jober/tests/app_test.py
fans/jober/tests/capture_test.py
fans/jober/tests/conftest.py
fans/jober/tests/job_test.py
fans/jober/tests/jober_test.py
fans/jober/tests/misc_test.py
fans/jober/tests/readme_test.py
fans/jober/tests/run_test.py
fans/jober/tests/target_test.py
fans/jober/tests/samples/__init__.py
fans/jober/tests/samples/echo.py
fans/jober/tests/samples/foo/foo/__init__.py
fans/jober/tests/samples/foo/foo/__main__.py
fans/jober/tests/usages/__init__.py
fans/jober/tests/usages/interval_test.py
fans/jober/tests/usages/module_test.py
fans/jober/tests/usages/quantix_test.py
fans/jober/tests/usages/run_test.py
fans/joberv1/__init__.py
fans/joberv1/app.py
fans/joberv1/errors.py
fans/joberv1/job.py
fans/joberv1/jober.py
fans/joberv1/run.py
fans/joberv1/utils.py
fans/nos/__init__.py
fans/nos/collection.py
fans/nos/cons.py
fans/nos/nos.py
fans/nos/store.py
fans/nos/tests/__init__.py
fans/nos/tests/nos_test.py
fans/nos/tests/readme_test.py
fans/os/__init__.py
fans/os/hotkey.py
fans-0.0.68.dist-info/METADATA
fans-0.0.68.dist-info/WHEEL
fans-0.0.68.dist-info/top_level.txt
fans-0.0.68.dist-info/RECORD
