Metadata-Version: 2.4
Name: fans
Version: 0.0.68
Summary: fans656's python library
Requires-Python: >=3.10
Requires-Dist: aiofiles>=25.1.0
Requires-Dist: apscheduler>=3.11.0
Requires-Dist: async-asgi-testclient>=1.4.11
Requires-Dist: build>=1.2.2.post1
Requires-Dist: deepmerge>=2.0
Requires-Dist: dill>=0.3.9
Requires-Dist: duf>=0.0.14
Requires-Dist: httpx>=0.28.1
Requires-Dist: janus>=2.0.0
Requires-Dist: msgpack>=1.1.0
Requires-Dist: peewee>=3.17.8
Requires-Dist: pytz>=2024.2
Requires-Dist: pyyaml>=6.0.2
Requires-Dist: requests>=2.32.3
Requires-Dist: sse-starlette>=3.0.3
Requires-Dist: sseclient>=0.0.27
Requires-Dist: tabulate>=0.9.0
Requires-Dist: werkzeug>=3.1.3
